{"stats":{"minecraft:mined":{"minecraft:short_grass":2,"minecraft:sand":14,"minecraft:oak_leaves":2,"minecraft:dirt":1,"minecraft:vine":2,"minecraft:oak_log":1,"minecraft:stripped_oak_log":1,"minecraft:grass_block":2,"minecraft:oak_planks":1,"minecraft:jungle_leaves":1,"minecraft:cocoa":6},"minecraft:custom":{"minecraft:time_since_rest":12920,"minecraft:walk_one_cm":19094,"minecraft:leave_game":28,"minecraft:walk_under_water_one_cm":1403,"minecraft:damage_taken":140,"minecraft:play_time":12920,"minecraft:jump":155,"minecraft:time_since_death":12920,"minecraft:drop":1,"minecraft:sprint_one_cm":1951,"minecraft:fall_one_cm":4469,"minecraft:total_world_time":12920,"minecraft:fly_one_cm":2809,"minecraft:walk_on_water_one_cm":567,"minecraft:crouch_one_cm":940,"minecraft:sneak_time":1350,"minecraft:climb_one_cm":4469},"minecraft:picked_up":{"minecraft:dirt":3,"minecraft:oak_log":1,"minecraft:stone_axe":1,"minecraft:sand":14,"minecraft:oak_planks":1,"minecraft:stripped_oak_log":1,"minecraft:cocoa_beans":18},"minecraft:crafted":{"minecraft:oak_planks":4},"minecraft:used":{"minecraft:stone_shovel":21,"minecraft:stone_axe":7,"minecraft:cocoa_beans":3,"minecraft:oak_planks":1},"minecraft:dropped":{"minecraft:stone_axe":1}},"DataVersion":4440}